formulas/__init__.py
formulas/_version.py
formulas/builder.py
formulas/cell.py
formulas/errors.py
formulas/parser.py
formulas/ranges.py
formulas/excel/__init__.py
formulas/excel/cycle.py
formulas/excel/ods_reader.py
formulas/excel/xlreader.py
formulas/functions/__init__.py
formulas/functions/comp.py
formulas/functions/date.py
formulas/functions/eng.py
formulas/functions/financial.py
formulas/functions/google.py
formulas/functions/info.py
formulas/functions/logic.py
formulas/functions/look.py
formulas/functions/math.py
formulas/functions/operators.py
formulas/functions/stat.py
formulas/functions/text.py
formulas/functions/units.json
formulas/tokens/__init__.py
formulas/tokens/function.py
formulas/tokens/operand.py
formulas/tokens/operator.py
formulas/tokens/parenthesis.py
formulas-1.3.2.dist-info/licenses/AUTHORS.rst
formulas-1.3.2.dist-info/licenses/LICENSE.txt
formulas-1.3.2.dist-info/METADATA
formulas-1.3.2.dist-info/WHEEL
formulas-1.3.2.dist-info/top_level.txt
formulas-1.3.2.dist-info/RECORD
